smc/__init__.py
smc/smc.py
smc-0.5.3.dist-info/LICENSE
smc-0.5.3.dist-info/WHEEL
smc-0.5.3.dist-info/METADATA
smc-0.5.3.dist-info/RECORD
