Metadata-Version: 2.1
Name: smc
Version: 0.5.3
Summary: A python driver library for Pololu's Simple Motor Controllers
Home-page: https://pypi.org/project/smc/
License: MIT
Keywords: framework,robotic,robot,motor controller
Author: walchko
Author-email: walchko@users.noreply.github.com
Requires-Python: >=3.6
Classifier: Development Status :: 4 - Beta
Classifier: License :: OSI Approved :: MIT License
Classifier: Operating System :: MacOS :: MacOS X
Classifier: Operating System :: POSIX
Classifier: Operating System :: POSIX :: Linux
Classifier: Operating System :: Unix
Classifier: Programming Language :: Python :: 3
Classifier: Programming Language :: Python :: 3.6
Classifier: Programming Language :: Python :: 3.7
Classifier: Programming Language :: Python :: 3.8
Classifier: Programming Language :: Python :: 3.9
Classifier: Topic :: Scientific/Engineering
Classifier: Topic :: Scientific/Engineering :: Artificial Intelligence
Classifier: Topic :: Scientific/Engineering :: Image Recognition
Classifier: Topic :: Software Development :: Libraries :: Python Modules
Requires-Dist: importlib-metadata; python_version < "3.8"
Requires-Dist: pyserial
Project-URL: Repository, http://github.com/MomsFriendlyRobotCompany/smc
